.gitignore
.gitlab-ci.yml
.travis.yml
MANIFEST.in
README.rst
dev_requirements.txt
requirements.txt
setup.cfg
setup.py
tox.ini
doc/ARCHITECTURE
doc/Changes
doc/INSTALL
doc/LICENSE
doc/TODO
doc/interface_class
doc/walker
m9s_PyWebDAV3.egg-info/PKG-INFO
m9s_PyWebDAV3.egg-info/SOURCES.txt
m9s_PyWebDAV3.egg-info/dependency_links.txt
m9s_PyWebDAV3.egg-info/entry_points.txt
m9s_PyWebDAV3.egg-info/not-zip-safe
m9s_PyWebDAV3.egg-info/top_level.txt
pywebdav/__init__.py
pywebdav/__main__.py
pywebdav/lib/AuthServer.py
pywebdav/lib/INI_Parse.py
pywebdav/lib/WebDAVServer.py
pywebdav/lib/__init__.py
pywebdav/lib/constants.py
pywebdav/lib/davcmd.py
pywebdav/lib/davcopy.py
pywebdav/lib/davmove.py
pywebdav/lib/dbconn.py
pywebdav/lib/delete.py
pywebdav/lib/errors.py
pywebdav/lib/iface.py
pywebdav/lib/locks.py
pywebdav/lib/propfind.py
pywebdav/lib/report.py
pywebdav/lib/status.py
pywebdav/lib/utils.py
pywebdav/server/__init__.py
pywebdav/server/config.ini
pywebdav/server/daemonize.py
pywebdav/server/fileauth.py
pywebdav/server/fshandler.py
pywebdav/server/mysqlauth.py
pywebdav/server/server.py
test/.gitignore
test/litmus-0.13.tar.gz
test/test_litmus.py